{"code":"2302","updated":"2026-07-09","y":{"2016":{"hi":7.38,"lo":5.32,"avg":6.1175,"pe":57.7182,"pb":0.6295,"yield":0.3155,"ref":6.38},"2017":{"hi":7.15,"lo":5.21,"avg":6.0642,"pe":null,"pb":0.6171,"yield":null,"ref":6.07},"2018":{"hi":12.3,"lo":5.28,"avg":7.6325,"pe":77.1429,"pb":0.7838,"yield":null,"ref":8.02},"2019":{"hi":11.5,"lo":7.18,"avg":8.7833,"pe":66.1095,"pb":0.8105,"yield":null,"ref":8.34},"2020":{"hi":28.75,"lo":4.43,"avg":11.3375,"pe":442.8261,"pb":2.2435,"yield":null,"ref":22.99},"2021":{"hi":26.3,"lo":14.6,"avg":19.5475,"pe":19.1891,"pb":1.5923,"yield":1.7773,"ref":16.96},"2022":{"hi":20.45,"lo":14.15,"avg":17.0733,"pe":17.3736,"pb":1.6141,"yield":3.3914,"ref":18.14},"2023":null,"2024":{"hi":21.5,"lo":15.2,"avg":18.5325,"pe":44.0177,"pb":1.7468,"yield":1.64,"ref":19.86},"2025":{"hi":24.3,"lo":14.8,"avg":18.1942,"pe":23.41,"pb":1.6718,"yield":3.2218,"ref":18.11}}}