{"code":"2497","updated":"2026-07-09","y":{"2016":{"hi":44.1,"lo":28.9,"avg":33.7058,"pe":null,"pb":null,"yield":null,"ref":32.42},"2017":{"hi":39.7,"lo":27.2,"avg":31.6842,"pe":null,"pb":2.0524,"yield":1.7157,"ref":29.6},"2018":{"hi":30.25,"lo":12.7,"avg":22.2192,"pe":null,"pb":1.2243,"yield":null,"ref":15.46},"2019":{"hi":28.85,"lo":15.3,"avg":22.1558,"pe":null,"pb":1.8391,"yield":null,"ref":22.69},"2020":{"hi":35.0,"lo":12.1,"avg":19.0142,"pe":null,"pb":2.6165,"yield":null,"ref":30.51},"2021":{"hi":91.0,"lo":25.4,"avg":41.4117,"pe":499.2636,"pb":7.3014,"yield":null,"ref":80.76},"2022":{"hi":117.5,"lo":59.7,"avg":83.2308,"pe":26.8605,"pb":4.8845,"yield":null,"ref":81.72},"2023":{"hi":82.3,"lo":60.4,"avg":71.61,"pe":29.5095,"pb":3.7519,"yield":1.0695,"ref":66.16},"2024":{"hi":90.7,"lo":48.2,"avg":63.6533,"pe":25.1559,"pb":3.1255,"yield":1.6309,"ref":61.65},"2025":{"hi":63.3,"lo":37.2,"avg":49.32,"pe":18.2714,"pb":2.485,"yield":4.315,"ref":51.74}}}