{"code":"3060","updated":"2026-07-10","y":{"2016":{"hi":60.6,"lo":28.55,"avg":43.45,"pe":18.4418,"pb":1.1445,"yield":12.4882,"ref":30.66},"2017":{"hi":38.4,"lo":25.7,"avg":31.1658,"pe":27.7357,"pb":0.9529,"yield":5.521,"ref":27.28},"2018":{"hi":28.2,"lo":14.0,"avg":20.4425,"pe":null,"pb":0.5633,"yield":3.961,"ref":15.48},"2019":{"hi":18.45,"lo":12.3,"avg":14.8492,"pe":null,"pb":0.5659,"yield":null,"ref":13.71},"2020":{"hi":17.9,"lo":9.9,"avg":14.0217,"pe":null,"pb":0.7226,"yield":null,"ref":15.77},"2021":{"hi":37.35,"lo":13.5,"avg":22.5058,"pe":64.9568,"pb":1.2532,"yield":null,"ref":27.19},"2022":{"hi":26.85,"lo":15.75,"avg":20.025,"pe":13.0264,"pb":0.79,"yield":5.9559,"ref":17.02},"2023":{"hi":24.0,"lo":15.95,"avg":18.9992,"pe":null,"pb":1.1095,"yield":1.4143,"ref":21.46},"2024":{"hi":38.7,"lo":19.4,"avg":26.71,"pe":null,"pb":1.2191,"yield":1.0491,"ref":24.24},"2025":{"hi":35.95,"lo":19.05,"avg":24.9033,"pe":null,"pb":1.6836,"yield":1.1386,"ref":32.34}}}