{"code":"4414","updated":"2026-07-10","y":{"2016":{"hi":28.25,"lo":16.2,"avg":20.5442,"pe":null,"pb":1.9823,"yield":null,"ref":17.82},"2017":{"hi":23.45,"lo":16.85,"avg":19.3775,"pe":null,"pb":1.0814,"yield":null,"ref":17.86},"2018":{"hi":19.4,"lo":11.8,"avg":15.0742,"pe":null,"pb":0.8452,"yield":null,"ref":13.62},"2019":{"hi":16.25,"lo":10.2,"avg":13.2333,"pe":null,"pb":0.8177,"yield":null,"ref":12.0},"2020":{"hi":16.95,"lo":7.48,"avg":11.47,"pe":null,"pb":0.9265,"yield":null,"ref":11.3},"2021":{"hi":12.3,"lo":6.42,"avg":9.1275,"pe":null,"pb":0.6105,"yield":null,"ref":7.02},"2022":{"hi":7.26,"lo":2.22,"avg":5.2038,"pe":null,"pb":null,"yield":null,"ref":5.2038},"2023":{"hi":5.65,"lo":3.21,"avg":3.9514,"pe":null,"pb":0.8286,"yield":null,"ref":3.7},"2024":{"hi":4.0,"lo":2.84,"avg":3.3108,"pe":null,"pb":0.7814,"yield":null,"ref":2.95},"2025":{"hi":14.0,"lo":2.78,"avg":7.1592,"pe":8.8418,"pb":0.7177,"yield":null,"ref":11.41}}}